sme.cpython-310-darwin.so
sme-1.10.1.dist-info/RECORD
sme-1.10.1.dist-info/WHEEL
sme-1.10.1.dist-info/METADATA
sme-1.10.1.dist-info/licenses/LICENSE
