Metadata-Version: 2.2
Name: sme
Version: 1.10.1
Summary: Spatial Model Editor python bindings
Author-Email: Liam Keegan <liam@keegan.ch>
License: MIT
Classifier: Topic :: Scientific/Engineering :: Bio-Informatics
Classifier: License :: OSI Approved :: MIT License
Classifier: Intended Audience :: Science/Research
Classifier: Intended Audience :: Education
Classifier: Natural Language :: English
Classifier: Programming Language :: C++
Classifier: Programming Language :: Python :: 3 :: Only
Classifier: Programming Language :: Python :: 3.8
Classifier: Programming Language :: Python :: 3.9
Classifier: Programming Language :: Python :: 3.10
Classifier: Programming Language :: Python :: 3.11
Classifier: Programming Language :: Python :: 3.12
Classifier: Programming Language :: Python :: 3.13
Classifier: Programming Language :: Python :: 3.14
Classifier: Programming Language :: Python :: Implementation :: CPython
Classifier: Operating System :: MacOS :: MacOS X
Classifier: Operating System :: Microsoft :: Windows
Classifier: Operating System :: POSIX :: Linux
Project-URL: Documentation, https://spatial-model-editor.readthedocs.io/
Project-URL: Github, https://github.com/spatial-model-editor/spatial-model-editor
Project-URL: Issues, https://github.com/spatial-model-editor/spatial-model-editor/issues
Project-URL: Try it online, https://colab.research.google.com/github/spatial-model-editor/spatial-model-editor/blob/main/docs/sme/notebooks/getting_started.ipynb
Requires-Python: >=3.8
Requires-Dist: numpy
Provides-Extra: test
Requires-Dist: pytest; extra == "test"
Requires-Dist: matplotlib; extra == "test"
